LICENSE.md
MANIFEST.in
PyPIREADME.md
setup.py
melissadatacloudapi/PostReqestBase.py
melissadatacloudapi/RecordRequests.py
melissadatacloudapi/__init__.py
melissadatacloudapi.egg-info/PKG-INFO
melissadatacloudapi.egg-info/SOURCES.txt
melissadatacloudapi.egg-info/dependency_links.txt
melissadatacloudapi.egg-info/top_level.txt
melissadatacloudapi/apiresponse/BusinessCoderResponse.py
melissadatacloudapi/apiresponse/ExpressEntryResponse.py
melissadatacloudapi/apiresponse/GlobalAddressVerificationResponse.py
melissadatacloudapi/apiresponse/GlobalEmailResponse.py
melissadatacloudapi/apiresponse/GlobalExpressEntryResponse.py
melissadatacloudapi/apiresponse/GlobalIPResponse.py
melissadatacloudapi/apiresponse/GlobalNameResponse.py
melissadatacloudapi/apiresponse/GlobalPhoneResponse.py
melissadatacloudapi/apiresponse/PeopleBusinessSearchResponse.py
melissadatacloudapi/apiresponse/PersonatorConsumerResponse.py
melissadatacloudapi/apiresponse/PersonatorIdentityResponse.py
melissadatacloudapi/apiresponse/PersonatorSearchResponse.py
melissadatacloudapi/apiresponse/PropertyResponse.py
melissadatacloudapi/apiresponse/ResponseBase.py
melissadatacloudapi/apiresponse/ReverseGeoCoderResponse.py
melissadatacloudapi/apiresponse/SSNNameMatchResponse.py
melissadatacloudapi/apiresponse/SmartMoverResponse.py
melissadatacloudapi/apiresponse/StreetRouteResponse.py
melissadatacloudapi/apiresponse/TokenServerResponse.py
melissadatacloudapi/apiresponse/__init__.py
melissadatacloudapi/cloudapis/BusinessCoder.py
melissadatacloudapi/cloudapis/CloudApiBase.py
melissadatacloudapi/cloudapis/GlobalAddressVerification.py
melissadatacloudapi/cloudapis/GlobalEmail.py
melissadatacloudapi/cloudapis/GlobalExpressEntry.py
melissadatacloudapi/cloudapis/GlobalIP.py
melissadatacloudapi/cloudapis/GlobalName.py
melissadatacloudapi/cloudapis/GlobalPhone.py
melissadatacloudapi/cloudapis/PeopleBusinessSearch.py
melissadatacloudapi/cloudapis/PersonatorConsumer.py
melissadatacloudapi/cloudapis/PersonatorIdentity.py
melissadatacloudapi/cloudapis/PersonatorSearch.py
melissadatacloudapi/cloudapis/Property.py
melissadatacloudapi/cloudapis/ReverseGeoCoder.py
