Metadata-Version: 2.4
Name: melissadatacloudapi
Version: 3.14.0
Home-page: https://github.com/MelissaData/MelissaCloudAPI-Python3
License-File: LICENSE.md
Dynamic: description
Dynamic: description-content-type
Dynamic: home-page
Dynamic: license-file
